model_evaluator/__init__.py
model_evaluator/metrics.py
model_evaluator/trainer.py
model_evaluator-0.0.2.dist-info/METADATA
model_evaluator-0.0.2.dist-info/WHEEL
model_evaluator-0.0.2.dist-info/top_level.txt
model_evaluator-0.0.2.dist-info/RECORD
